{
  "experiment_name": "Metaworld-Sweep-Into",
  "experiment_id": 15,
  "env_name": "metaworld-sweep-into-v2",
  "checkpoints": [
    200000,
    400000,
    600000,
    800000,
    1000000,
    1150000
  ],
  "projection_method": "PCA",
  "projection_props": {
    "n_components": 2
  },
  "sequence_length": 1,
  "step_range": "[]",
  "reproject": false,
  "append_time": false,
  "transition_embedding": true,
  "feature_embedding": true,
  "handler_path": "data/saved_projections/joint/metaworld-sweep-into-v2_15_joint_PCA_200000_1150000_handler.pkl",
  "results_path": "data/saved_projections/joint/metaworld-sweep-into-v2_15_joint_PCA_200000_1150000_results.npz"
}